{
    "todoList": [{
            "id": 1,
            "name": "quét nhà",
            "completed": true,
            "lastViewed": 1718127339393
        },
        {
            "id": 2,
            "name": "Giặt quần áo",
            "completed": true
        },
        {
            "id": 3,
            "name": "Nấu cơm",
            "completed": true
        },
        {
            "id": 5,
            "name": "xem ti vi",
            "completed": false
        },
        {
            "name": "jnv",
            "completed": false,
            "id": 6
        },
        {
            "name": "vhbdj",
            "completed": false,
            "id": 7
        },
        {
            "name": "jcb ",
            "completed": false,
            "created_at": "2024-06-11T18:51:57.748Z",
            "id": 8
        }
    ]
}